solar_and_storage/__init__.py
solar_and_storage/example.py
solar_and_storage/solar_and_storage.py
solar_and_storage-0.0.11.dist-info/LICENSE
solar_and_storage-0.0.11.dist-info/METADATA
solar_and_storage-0.0.11.dist-info/WHEEL
solar_and_storage-0.0.11.dist-info/top_level.txt
solar_and_storage-0.0.11.dist-info/RECORD
