Metadata-Version: 2.2
Name: solar_and_storage
Version: 0.0.11
Summary: Modelling for Solar and Storage
Author: Peter Dudfield
Author-email: info@openclimatefix.org
License: MIT
License-File: LICENSE
Requires-Dist: pandas
Requires-Dist: scipy==1.8.1
Requires-Dist: cvxopt
Requires-Dist: cvxpy==1.2.2
Requires-Dist: plotly
Requires-Dist: kaleido
Dynamic: author
Dynamic: author-email
Dynamic: description
Dynamic: description-content-type
Dynamic: license
Dynamic: requires-dist
Dynamic: summary
